[
    {
        "model": "areas.area",
        "pk": 1,
        "fields": {
            "name": "Home",
            "parent_area": null
        }
    },
    {
        "model": "areas.area",
        "pk": 2,
        "fields": {
            "name": "Upstairs Bathroom",
            "parent_area": 1
        }
    },
    {
        "model": "areas.area",
        "pk": 3,
        "fields": {
            "name": "Bathtube",
            "parent_area": 2
        }
    },
    {
        "model": "areas.area",
        "pk": 4,
        "fields": {
            "name": "Yard",
            "parent_area": 1
        }
    }
]
